[
    {
        "title": "Playing The Sims for science",
        "original_title": "De Sims voor de wetenschap",
        "desciprtion": "In this video, I try to explain to the students of the Faculty of Arts how computer simulations can be used in the humanities — and how they are a distant cousin of The Sims.",
        "context": "L-Dataverwerking",
        "produced_for": [ "Margherita Fantoli" ],
        "link": "https://youtu.be/zDR9zkIhf-M",
        "date": "2024-11-04"
    },
    {
        "title": "Why do the Dutch and the Flemish sound different?",
        "original_title": "Waarom klinken Nederlanders en Vlamingen anders?",
        "desciprtion": "I made this video to explain to the students of the Faculty of Arts how we can use computer simulations to find out why speakers of Belgian and Dutch standard language do not sound the same.",
        "context": "L-Dataverwerking",
        "produced_for": [ "Margherita Fantoli" ],
        "link": "https://youtu.be/F2mGqyzjKHk",
        "date": "2024-11-04"
    }
]